keyauthru/__init__.py
keyauthru/keyauthru.py
KeyAuth.ru-1.2.1.dist-info/LICENSE
KeyAuth.ru-1.2.1.dist-info/METADATA
KeyAuth.ru-1.2.1.dist-info/WHEEL
KeyAuth.ru-1.2.1.dist-info/top_level.txt
KeyAuth.ru-1.2.1.dist-info/RECORD
