Metadata-Version: 2.1
Name: KeyAuth.ru
Version: 1.2.1
Summary: KeyAuth.ru API Wrapper for Python
Home-page: https://gist.github.com/ttwizz/88ded5b95c6b52c65e50196f555b51cd
Author: ttwiz_z
Author-email: moderkascriptsltd@gmail.com
Project-URL: Author, https://github.com/ttwizz
Project-URL: Organization, https://github.com/ModerkaScripts
Keywords: KeyAuth.ru
Classifier: Programming Language :: Python :: 3.10
Classifier: License :: OSI Approved :: MIT License
Classifier: Operating System :: OS Independent
Requires-Python: >=3.8
License-File: LICENSE
Requires-Dist: requests >=2.31.0
Requires-Dist: pywin32 >=306
